LICENSE.txt
MANIFEST.in
setup.py
rxtender/__init__.py
rxtender/rxtender.ebnf
rxtender/rxtender.py
rxtender.egg-info/PKG-INFO
rxtender.egg-info/SOURCES.txt
rxtender.egg-info/dependency_links.txt
rxtender.egg-info/requires.txt
rxtender.egg-info/top_level.txt
script/rxtender
test/__init__.py
test/test_parser_stream.py
test/test_parser_struct.py